F2_V_1_5/Triwave_Generator.v
module Triwave_Generator(input wire sysclk,
input wire Enable_SW_2,
output wire Pulse);
reg [5:0] count = 0;
reg [5:0] DC_Index = 0;
reg [5:0] Duty_Cycle = 0;
assign Pulse = (count < Duty_Cycle & Enable_SW_2);
always @(posedge sysclk)begin
	count<=count+1'b1;	
	if (&count==1)
		DC_Index<=DC_Index+1'b1;
	end
always @ (DC_Index) begin
	if (6'd0<DC_Index & DC_Index<6'd32)begin
		Duty_Cycle <= Duty_Cycle + 2'd2;
	end else if (DC_Index == 6'd32)begin
		Duty_Cycle <= 6'd62;
	end else if (6'd31<DC_Index & DC_Index<7'd64) begin
		Duty_Cycle <= Duty_Cycle - 2'd2;
	end
end
endmodule

F2_V_1_5/TB/TB_Triwave_Generator.v
//TB_Triwave_Generator.v
//`include"Triwave_Generator.v"
`timescale 1ns / 1ns
module TB_Triwave_Generator;
wire Pulse;
reg Enable_SW_2;
reg clock;

Triwave_Generator UUT(
.Pulse(Pulse),
.Enable_SW_2(Enable_SW_2),
.sysclk(clock));

initial begin: clockdef // clock definition block (only useful for synchroniser)
	clock = 1'b1;
	forever #10 clock=~clock; //the clock flips every 5ns
end

initial begin
   $dumpfile("Triwave_Generator.vcd");
   $dumpvars(Pulse);
end

initial begin: stopat
   #500000; $finish;
end

initial begin: signals
	Enable_SW_2 = 1;
end

endmodule

F2/Triwave_Generator.vcd
$date
	Wed Apr 15 12:26:56 2015
$end
$version
	Icarus Verilog
$end
$timescale
	1ns
$end
$scope module TB_Triwave_Generator $end
$var wire 1 ! Pulse $end
$var reg 1 " Enable_SW_2 $end
$var reg 1 # clock $end
$scope module UUT $end
$var wire 1 $ Enable_SW_2 $end
$var wire 1 ! Pulse $end
$var wire 1 % sysclk $end
$var reg 6 & DC_Index [5:0] $end
$var reg 6 ' Duty_Cycle [5:0] $end
$var reg 6 ( count [5:0] $end
$upscope $end
$scope begin clockdef $end
$upscope $end
$scope begin stopat $end
$upscope $end
$scope begin signals $end
$upscope $end
$upscope $end
$enddefinitions $end
#0
$dumpvars
b1 (
b0 '
b0 &
1%
1$
1#
1"
0!
$end
#10
0#
0%
#20
b10 (
1#
1%
#30
0#
0%
#40
b11 (
1#
1%
#50
0#
0%
#60
b100 (
1#
1%
#70
0#
0%
#80
b101 (
1#
1%
#90
0#
0%
#100
b110 (
1#
1%
#110
0#
0%
#120
b111 (
1#
1%
#130
0#
0%
#140
b1000 (
1#
1%
#150
0#
0%
#160
b1001 (
1#
1%
#170
0#
0%
#180
b1010 (
1#
1%
#190
0#
0%
#200
b1011 (
1#
1%
#210
0#
0%
#220
b1100 (
1#
1%
#230
0#
0%
#240
b1101 (
1#
1%
#250
0#
0%
#260
b1110 (
1#
1%
#270
0#
0%
#280
b1111 (
1#
1%
#290
0#
0%
#300
b10000 (
1#
1%
#310
0#
0%
#320
b10001 (
1#
1%
#330
0#
0%
#340
b10010 (
1#
1%
#350
0#
0%
#360
b10011 (
1#
1%
#370
0#
0%
#380
b10100 (
1#
1%
#390
0#
0%
#400
b10101 (
1#
1%
#410
0#
0%
#420
b10110 (
1#
1%
#430
0#
0%
#440
b10111 (
1#
1%
#450
0#
0%
#460
b11000 (
1#
1%
#470
0#
0%
#480
b11001 (
1#
1%
#490
0#
0%
#500
b11010 (
1#
1%
#510
0#
0%
#520
b11011 (
1#
1%
#530
0#
0%
#540
b11100 (
1#
1%
#550
0#
0%
#560
b11101 (
1#
1%
#570
0#
0%
#580
b11110 (
1#
1%
#590
0#
0%
#600
b11111 (
1#
1%
#610
0#
0%
#620
b100000 (
1#
1%
#630
0#
0%
#640
b100001 (
1#
1%
#650
0#
0%
#660
b100010 (
1#
1%
#670
0#
0%
#680
b100011 (
1#
1%
#690
0#
0%
#700
b100100 (
1#
1%
#710
0#
0%
#720
b100101 (
1#
1%
#730
0#
0%
#740
b100110 (
1#
1%
#750
0#
0%
#760
b100111 (
1#
1%
#770
0#
0%
#780
b101000 (
1#
1%
#790
0#
0%
#800
b101001 (
1#
1%
#810
0#
0%
#820
b101010 (
1#
1%
#830
0#
0%
#840
b101011 (
1#
1%
#850
0#
0%
#860
b101100 (
1#
1%
#870
0#
0%
#880
b101101 (
1#
1%
#890
0#
0%
#900
b101110 (
1#
1%
#910
0#
0%
#920
b101111 (
1#
1%
#930
0#
0%
#940
b110000 (
1#
1%
#950
0#
0%
#960
b110001 (
1#
1%
#970
0#
0%
#980
b110010 (
1#
1%
#990
0#
0%
#1000
b110011 (
1#
1%
#1010
0#
0%
#1020
b110100 (
1#
1%
#1030
0#
0%
#1040
b110101 (
1#
1%
#1050
0#
0%
#1060
b110110 (
1#
1%
#1070
0#
0%
#1080
b110111 (
1#
1%
#1090
0#
0%
#1100
b111000 (
1#
1%
#1110
0#
0%
#1120
b111001 (
1#
1%
#1130
0#
0%
#1140
b111010 (
1#
1%
#1150
0#
0%
#1160
b111011 (
1#
1%
#1170
0#
0%
#1180
b111100 (
1#
1%
#1190
0#
0%
#1200
b111101 (
1#
1%
#1210
0#
0%
#1220
b111110 (
1#
1%
#1230
0#
0%
#1240
b111111 (
1#
1%
#1250
0#
0%
#1260
1!
b10 '
b1 &
b0 (
1#
1%
#1270
0#
0%
#1280
b1 (
1#
1%
#1290
0#
0%
#1300
0!
b10 (
1#
1%
#1310
0#
0%
#1320
b11 (
1#
1%
#1330
0#
0%
#1340
b100 (
1#
1%
#1350
0#
0%
#1360
b101 (
1#
1%
#1370
0#
0%
#1380
b110 (
1#
1%
#1390
0#
0%
#1400
b111 (
1#
1%
#1410
0#
0%
#1420
b1000 (
1#
1%
#1430
0#
0%
#1440
b1001 (
1#
1%
#1450
0#
0%
#1460
b1010 (
1#
1%
#1470
0#
0%
#1480
b1011 (
1#
1%
#1490
0#
0%
#1500
b1100 (
1#
1%
#1510
0#
0%
#1520
b1101 (
1#
1%
#1530
0#
0%
#1540
b1110 (
1#
1%
#1550
0#
0%
#1560
b1111 (
1#
1%
#1570
0#
0%
#1580
b10000 (
1#
1%
#1590
0#
0%
#1600
b10001 (
1#
1%
#1610
0#
0%
#1620
b10010 (
1#
1%
#1630
0#
0%
#1640
b10011 (
1#
1%
#1650
0#
0%
#1660
b10100 (
1#
1%
#1670
0#
0%
#1680
b10101 (
1#
1%
#1690
0#
0%
#1700
b10110 (
1#
1%
#1710
0#
0%
#1720
b10111 (
1#
1%
#1730
0#
0%
#1740
b11000 (
1#
1%
#1750
0#
0%
#1760
b11001 (
1#
1%
#1770
0#
0%
#1780
b11010 (
1#
1%
#1790
0#
0%
#1800
b11011 (
1#
1%
#1810
0#
0%
#1820
b11100 (
1#
1%
#1830
0#
0%
#1840
b11101 (
1#
1%
#1850
0#
0%
#1860
b11110 (
1#
1%
#1870
0#
0%
#1880
b11111 (
1#
1%
#1890
0#
0%
#1900
b100000 (
1#
1%
#1910
0#
0%
#1920
b100001 (
1#
1%
#1930
0#
0%
#1940
b100010 (
1#
1%
#1950
0#
0%
#1960
b100011 (
1#
1%
#1970
0#
0%
#1980
b100100 (
1#
1%
#1990
0#
0%
#2000
b100101 (
1#
1%
#2010
0#
0%
#2020
b100110 (
1#
1%
#2030
0#
0%
#2040
b100111 (
1#
1%
#2050
0#
0%
#2060
b101000 (
1#
1%
#2070
0#
0%
#2080
b101001 (
1#
1%
#2090
0#
0%
#2100
b101010 (
1#
1%
#2110
0#
0%
#2120
b101011 (
1#
1%
#2130
0#
0%
#2140
b101100 (
1#
1%
#2150
0#
0%
#2160
b101101 (
1#
1%
#2170
0#
0%
#2180
b101110 (
1#
1%
#2190
0#
0%
#2200
b101111 (
1#
1%
#2210
0#
0%
#2220
b110000 (
1#
1%
#2230
0#
0%
#2240
b110001 (
1#
1%
#2250
0#
0%
#2260
b110010 (
1#
1%
#2270
0#
0%
#2280
b110011 (
1#
1%
#2290
0#
0%
#2300
b110100 (
1#
1%
#2310
0#
0%
#2320
b110101 (
1#
1%
#2330
0#
0%
#2340
b110110 (
1#
1%
#2350
0#
0%
#2360
b110111 (
1#
1%
#2370
0#
0%
#2380
b111000 (
1#
1%
#2390
0#
0%
#2400
b111001 (
1#
1%
#2410
0#
0%
#2420
b111010 (
1#
1%
#2430
0#
0%
#2440
b111011 (
1#
1%
#2450
0#
0%
#2460
b111100 (
1#
1%
#2470
0#
0%
#2480
b111101 (
1#
1%
#2490
0#
0%
#2500
b111110 (
1#
1%
#2510
0#
0%
#2520
b111111 (
1#
1%
#2530
0#
0%
#2540
b100 '
1!
b10 &
b0 (
1#
1%
#2550
0#
0%
#2560
b1 (
1#
1%
#2570
0#
0%
#2580
b10 (
1#
1%
#2590
0#
0%
#2600
b11 (
1#
1%
#2610
0#
0%
#2620
0!
b100 (
1#
1%
#2630
0#
0%
#2640
b101 (
1#
1%
#2650
0#
0%
#2660
b110 (
1#
1%
#2670
0#
0%
#2680
b111 (
1#
1%
#2690
0#
0%
#2700
b1000 (
1#
1%
#2710
0#
0%
#2720
b1001 (
1#
1%
#2730
0#
0%
#2740
b1010 (
1#
1%
#2750
0#
0%
#2760
b1011 (
1#
1%
#2770
0#
0%
#2780
b1100 (
1#
1%
#2790
0#
0%
#2800
b1101 (
1#
1%
#2810
0#
0%
#2820
b1110 (
1#
1%
#2830
0#
0%
#2840
b1111 (
1#
1%
#2850
0#
0%
#2860
b10000 (
1#
1%
#2870
0#
0%
#2880
b10001 (
1#
1%
#2890
0#
0%
#2900
b10010 (
1#
1%
#2910
0#
0%
#2920
b10011 (
1#
1%
#2930
0#
0%
#2940
b10100 (
1#
1%
#2950
0#
0%
#2960
b10101 (
1#
1%
#2970
0#
0%
#2980
b10110 (
1#
1%
#2990
0#
0%
#3000
b10111 (
1#
1%
#3010
0#
0%
#3020
b11000 (
1#
1%
#3030
0#
0%
#3040
b11001 (
1#
1%
#3050
0#
0%
#3060
b11010 (
1#
1%
#3070
0#
0%
#3080
b11011 (
1#
1%
#3090
0#
0%
#3100
b11100 (
1#
1%
#3110
0#
0%
#3120
b11101 (
1#
1%
#3130
0#
0%
#3140
b11110 (
1#
1%
#3150
0#
0%
#3160
b11111 (
1#
1%
#3170
0#
0%
#3180
b100000 (
1#
1%
#3190
0#
0%
#3200
b100001 (
1#
1%
#3210
0#
0%
#3220
b100010 (
1#
1%
#3230
0#
0%
#3240
b100011 (
1#
1%
#3250
0#
0%
#3260
b100100 (
1#
1%
#3270
0#
0%
#3280
b100101 (
1#
1%
#3290
0#
0%
#3300
b100110 (
1#
1%
#3310
0#
0%
#3320
b100111 (
1#
1%
#3330
0#
0%
#3340
b101000 (
1#
1%
#3350
0#
0%
#3360
b101001 (
1#
1%
#3370
0#
0%
#3380
b101010 (
1#
1%
#3390
0#
0%
#3400
b101011 (
1#
1%
#3410
0#
0%
#3420
b101100 (
1#
1%
#3430
0#
0%
#3440
b101101 (
1#
1%
#3450
0#
0%
#3460
b101110 (
1#
1%
#3470
0#
0%
#3480
b101111 (
1#
1%
#3490
0#
0%
#3500
b110000 (
1#
1%
#3510
0#
0%
#3520
b110001 (
1#
1%
#3530
0#
0%
#3540
b110010 (
1#
1%
#3550
0#
0%
#3560
b110011 (
1#
1%
#3570
0#
0%
#3580
b110100 (
1#
1%
#3590
0#
0%
#3600
b110101 (
1#
1%
#3610
0#
0%
#3620
b110110 (
1#
1%
#3630
0#
0%
#3640
b110111 (
1#
1%
#3650
0#
0%
#3660
b111000 (
1#
1%
#3670
0#
0%
#3680
b111001 (
1#
1%
#3690
0#
0%
#3700
b111010 (
1#
1%
#3710
0#
0%
#3720
b111011 (
1#
1%
#3730
0#
0%
#3740
b111100 (
1#
1%
#3750
0#
0%
#3760
b111101 (
1#
1%
#3770
0#
0%
#3780
b111110 (
1#
1%
#3790
0#
0%
#3800
b111111 (
1#
1%
#3810
0#
0%
#3820
b110 '
1!
b11 &
b0 (
1#
1%
#3830
0#
0%
#3840
b1 (
1#
1%
#3850
0#
0%
#3860
b10 (
1#
1%
#3870
0#
0%
#3880
b11 (
1#
1%
#3890
0#
0%
#3900
b100 (
1#
1%
#3910
0#
0%
#3920
b101 (
1#
1%
#3930
0#
0%
#3940
0!
b110 (
1#
1%
#3950
0#
0%
#3960
b111 (
1#
1%
#3970
0#
0%
#3980
b1000 (
1#
1%
#3990
0#
0%
#4000
b1001 (
1#
1%
#4010
0#
0%
#4020
b1010 (
1#
1%
#4030
0#
0%
#4040
b1011 (
1#
1%
#4050
0#
0%
#4060
b1100 (
1#
1%
#4070
0#
0%
#4080
b1101 (
1#
1%
#4090
0#
0%
#4100
b1110 (
1#
1%
#4110
0#
0%
#4120
b1111 (
1#
1%
#4130
0#
0%
#4140
b10000 (
1#
1%
#4150
0#
0%
#4160
b10001 (
1#
1%
#4170
0#
0%
#4180
b10010 (
1#
1%
#4190
0#
0%
#4200
b10011 (
1#
1%
#4210
0#
0%
#4220
b10100 (
1#
1%
#4230
0#
0%
#4240
b10101 (
1#
1%
#4250
0#
0%
#4260
b10110 (
1#
1%
#4270
0#
0%
#4280
b10111 (
1#
1%
#4290
0#
0%
#4300
b11000 (
1#
1%
#4310
0#
0%
#4320
b11001 (
1#
1%
#4330
0#
0%
#4340
b11010 (
1#
1%
#4350
0#
0%
#4360
b11011 (
1#
1%
#4370
0#
0%
#4380
b11100 (
1#
1%
#4390
0#
0%
#4400
b11101 (
1#
1%
#4410
0#
0%
#4420
b11110 (
1#
1%
#4430
0#
0%
#4440
b11111 (
1#
1%
#4450
0#
0%
#4460
b100000 (
1#
1%
#4470
0#
0%
#4480
b100001 (
1#
1%
#4490
0#
0%
#4500
b100010 (
1#
1%
#4510
0#
0%
#4520
b100011 (
1#
1%
#4530
0#
0%
#4540
b100100 (
1#
1%
#4550
0#
0%
#4560
b100101 (
1#
1%
#4570
0#
0%
#4580
b100110 (
1#
1%
#4590
0#
0%
#4600
b100111 (
1#
1%
#4610
0#
0%
#4620
b101000 (
1#
1%
#4630
0#
0%
#4640
b101001 (
1#
1%
#4650
0#
0%
#4660
b101010 (
1#
1%
#4670
0#
0%
#4680
b101011 (
1#
1%
#4690
0#
0%
#4700
b101100 (
1#
1%
#4710
0#
0%
#4720
b101101 (
1#
1%
#4730
0#
0%
#4740
b101110 (
1#
1%
#4750
0#
0%
#4760
b101111 (
1#
1%
#4770
0#
0%
#4780
b110000 (
1#
1%
#4790
0#
0%
#4800
b110001 (
1#
1%
#4810
0#
0%
#4820
b110010 (
1#
1%
#4830
0#
0%
#4840
b110011 (
1#
1%
#4850
0#
0%
#4860
b110100 (
1#
1%
#4870
0#
0%
#4880
b110101 (
1#
1%
#4890
0#
0%
#4900
b110110 (
1#
1%
#4910
0#
0%
#4920
b110111 (
1#
1%
#4930
0#
0%
#4940
b111000 (
1#
1%
#4950
0#
0%
#4960
b111001 (
1#
1%
#4970
0#
0%
#4980
b111010 (
1#
1%
#4990
0#
0%
#5000
b111011 (
1#
1%
#5010
0#
0%
#5020
b111100 (
1#
1%
#5030
0#
0%
#5040
b111101 (
1#
1%
#5050
0#
0%
#5060
b111110 (
1#
1%
#5070
0#
0%
#5080
b111111 (
1#
1%
#5090
0#
0%
#5100
b1000 '
1!
b100 &
b0 (
1#
1%
#5110
0#
0%
#5120
b1 (
1#
1%
#5130
0#
0%
#5140
b10 (
1#
1%
#5150
0#
0%
#5160
b11 (
1#
1%
#5170
0#
0%
#5180
b100 (
1#
1%
#5190
0#
0%
#5200
b101 (
1#
1%
#5210
0#
0%
#5220
b110 (
1#
1%
#5230
0#
0%
#5240
b111 (
1#
1%
#5250
0#
0%
#5260
0!
b1000 (
1#
1%
#5270
0#
0%
#5280
b1001 (
1#
1%
#5290
0#
0%
#5300
b1010 (
1#
1%
#5310
0#
0%
#5320
b1011 (
1#
1%
#5330
0#
0%
#5340
b1100 (
1#
1%
#5350
0#
0%
#5360
b1101 (
1#
1%
#5370
0#
0%
#5380
b1110 (
1#
1%
#5390
0#
0%
#5400
b1111 (
1#
1%
#5410
0#
0%
#5420
b10000 (
1#
1%
#5430
0#
0%
#5440
b10001 (
1#
1%
#5450
0#
0%
#5460
b10010 (
1#
1%
#5470
0#
0%
#5480
b10011 (
1#
1%
#5490
0#
0%
#5500
b10100 (
1#
1%
#5510
0#
0%
#5520
b10101 (
1#
1%
#5530
0#
0%
#5540
b10110 (
1#
1%
#5550
0#
0%
#5560
b10111 (
1#
1%
#5570
0#
0%
#5580
b11000 (
1#
1%
#5590
0#
0%
#5600
b11001 (
1#
1%
#5610
0#
0%
#5620
b11010 (
1#
1%
#5630
0#
0%
#5640
b11011 (
1#
1%
#5650
0#
0%
#5660
b11100 (
1#
1%
#5670
0#
0%
#5680
b11101 (
1#
1%
#5690
0#
0%
#5700
b11110 (
1#
1%
#5710
0#
0%
#5720
b11111 (
1#
1%
#5730
0#
0%
#5740
b100000 (
1#
1%
#5750
0#
0%
#5760
b100001 (
1#
1%
#5770
0#
0%
#5780
b100010 (
1#
1%
#5790
0#
0%
#5800
b100011 (
1#
1%
#5810
0#
0%
#5820
b100100 (
1#
1%
#5830
0#
0%
#5840
b100101 (
1#
1%
#5850
0#
0%
#5860
b100110 (
1#
1%
#5870
0#
0%
#5880
b100111 (
1#
1%
#5890
0#
0%
#5900
b101000 (
1#
1%
#5910
0#
0%
#5920
b101001 (
1#
1%
#5930
0#
0%
#5940
b101010 (
1#
1%
#5950
0#
0%
#5960
b101011 (
1#
1%
#5970
0#
0%
#5980
b101100 (
1#
1%
#5990
0#
0%
#6000
b101101 (
1#
1%
#6010
0#
0%
#6020
b101110 (
1#
1%
#6030
0#
0%
#6040
b101111 (
1#
1%
#6050
0#
0%
#6060
b110000 (
1#
1%
#6070
0#
0%
#6080
b110001 (
1#
1%
#6090
0#
0%
#6100
b110010 (
1#
1%
#6110
0#
0%
#6120
b110011 (
1#
1%
#6130
0#
0%
#6140
b110100 (
1#
1%
#6150
0#
0%
#6160
b110101 (
1#
1%
#6170
0#
0%
#6180
b110110 (
1#
1%
#6190
0#
0%
#6200
b110111 (
1#
1%
#6210
0#
0%
#6220
b111000 (
1#
1%
#6230
0#
0%
#6240
b111001 (
1#
1%
#6250
0#
0%
#6260
b111010 (
1#
1%
#6270
0#
0%
#6280
b111011 (
1#
1%
#6290
0#
0%
#6300
b111100 (
1#
1%
#6310
0#
0%
#6320
b111101 (
1#
1%
#6330
0#
0%
#6340
b111110 (
1#
1%
#6350
0#
0%
#6360
b111111 (
1#
1%
#6370
0#
0%
#6380
b1010 '
1!
b101 &
b0 (
1#
1%
#6390
0#
0%
#6400
b1 (
1#
1%
#6410
0#
0%
#6420
b10 (
1#
1%
#6430
0#
0%
#6440
b11 (
1#
1%
#6450
0#
0%
#6460
b100 (
1#
1%
#6470
0#
0%
#6480
b101 (
1#
1%
#6490
0#
0%
#6500
b110 (
1#
1%
#6510
0#
0%
#6520
b111 (
1#
1%
#6530
0#
0%
#6540
b1000 (
1#
1%
#6550
0#
0%
#6560
b1001 (
1#
1%
#6570
0#
0%
#6580
0!
b1010 (
1#
1%
#6590
0#
0%
#6600
b1011 (
1#
1%
#6610
0#
0%
#6620
b1100 (
1#
1%
#6630
0#
0%
#6640
b1101 (
1#
1%
#6650
0#
0%
#6660
b1110 (
1#
1%
#6670
0#
0%
#6680
b1111 (
1#
1%
#6690
0#
0%
#6700
b10000 (
1#
1%
#6710
0#
0%
#6720
b10001 (
1#
1%
#6730
0#
0%
#6740
b10010 (
1#
1%
#6750
0#
0%
#6760
b10011 (
1#
1%
#6770
0#
0%
#6780
b10100 (
1#
1%
#6790
0#
0%
#6800
b10101 (
1#
1%
#6810
0#
0%
#6820
b10110 (
1#
1%
#6830
0#
0%
#6840
b10111 (
1#
1%
#6850
0#
0%
#6860
b11000 (
1#
1%
#6870
0#
0%
#6880
b11001 (
1#
1%
#6890
0#
0%
#6900
b11010 (
1#
1%
#6910
0#
0%
#6920
b11011 (
1#
1%
#6930
0#
0%
#6940
b11100 (
1#
1%
#6950
0#
0%
#6960
b11101 (
1#
1%
#6970
0#
0%
#6980
b11110 (
1#
1%
#6990
0#
0%
#7000
b11111 (
1#
1%
#7010
0#
0%
#7020
b100000 (
1#
1%
#7030
0#
0%
#7040
b100001 (
1#
1%
#7050
0#
0%
#7060
b100010 (
1#
1%
#7070
0#
0%
#7080
b100011 (
1#
1%
#7090
0#
0%
#7100
b100100 (
1#
1%
#7110
0#
0%
#7120
b100101 (
1#
1%
#7130
0#
0%
#7140
b100110 (
1#
1%
#7150
0#
0%
#7160
b100111 (
1#
1%
#7170
0#
0%
#7180
b101000 (
1#
1%
#7190
0#
0%
#7200
b101001 (
1#
1%
#7210
0#
0%
#7220
b101010 (
1#
1%
#7230
0#
0%
#7240
b101011 (
1#
1%
#7250
0#
0%
#7260
b101100 (
1#
1%
#7270
0#
0%
#7280
b101101 (
1#
1%
#7290
0#
0%
#7300
b101110 (
1#
1%
#7310
0#
0%
#7320
b101111 (
1#
1%
#7330
0#
0%
#7340
b110000 (
1#
1%
#7350
0#
0%
#7360
b110001 (
1#
1%
#7370
0#
0%
#7380
b110010 (
1#
1%
#7390
0#
0%
#7400
b110011 (
1#
1%
#7410
0#
0%
#7420
b110100 (
1#
1%
#7430
0#
0%
#7440
b110101 (
1#
1%
#7450
0#
0%
#7460
b110110 (
1#
1%
#7470
0#
0%
#7480
b110111 (
1#
1%
#7490
0#
0%
#7500
b111000 (
1#
1%
#7510
0#
0%
#7520
b111001 (
1#
1%
#7530
0#
0%
#7540
b111010 (
1#
1%
#7550
0#
0%
#7560
b111011 (
1#
1%
#7570
0#
0%
#7580
b111100 (
1#
1%
#7590
0#
0%
#7600
b111101 (
1#
1%
#7610
0#
0%
#7620
b111110 (
1#
1%
#7630
0#
0%
#7640
b111111 (
1#
1%
#7650
0#
0%
#7660
b1100 '
1!
b110 &
b0 (
1#
1%
#7670
0#
0%
#7680
b1 (
1#
1%
#7690
0#
0%
#7700
b10 (
1#
1%
#7710
0#
0%
#7720
b11 (
1#
1%
#7730
0#
0%
#7740
b100 (
1#
1%
#7750
0#
0%
#7760
b101 (
1#
1%
#7770
0#
0%
#7780
b110 (
1#
1%
#7790
0#
0%
#7800
b111 (
1#
1%
#7810
0#
0%
#7820
b1000 (
1#
1%
#7830
0#
0%
#7840
b1001 (
1#
1%
#7850
0#
0%
#7860
b1010 (
1#
1%
#7870
0#
0%
#7880
b1011 (
1#
1%
#7890
0#
0%
#7900
0!
b1100 (
1#
1%
#7910
0#
0%
#7920
b1101 (
1#
1%
#7930
0#
0%
#7940
b1110 (
1#
1%
#7950
0#
0%
#7960
b1111 (
1#
1%
#7970
0#
0%
#7980
b10000 (
1#
1%
#7990
0#
0%
#8000
b10001 (
1#
1%
#8010
0#
0%
#8020
b10010 (
1#
1%
#8030
0#
0%
#8040
b10011 (
1#
1%
#8050
0#
0%
#8060
b10100 (
1#
1%
#8070
0#
0%
#8080
b10101 (
1#
1%
#8090
0#
0%
#8100
b10110 (
1#
1%
#8110
0#
0%
#8120
b10111 (
1#
1%
#8130
0#
0%
#8140
b11000 (
1#
1%
#8150
0#
0%
#8160
b11001 (
1#
1%
#8170
0#
0%
#8180
b11010 (
1#
1%
#8190
0#
0%
#8200
b11011 (
1#
1%
#8210
0#
0%
#8220
b11100 (
1#
1%
#8230
0#
0%
#8240
b11101 (
1#
1%
#8250
0#
0%
#8260
b11110 (
1#
1%
#8270
0#
0%
#8280
b11111 (
1#
1%
#8290
0#
0%
#8300
b100000 (
1#
1%
#8310
0#
0%
#8320
b100001 (
1#
1%
#8330
0#
0%
#8340
b100010 (
1#
1%
#8350
0#
0%
#8360
b100011 (
1#
1%
#8370
0#
0%
#8380
b100100 (
1#
1%
#8390
0#
0%
#8400
b100101 (
1#
1%
#8410
0#
0%
#8420
b100110 (
1#
1%
#8430
0#
0%
#8440
b100111 (
1#
1%
#8450
0#
0%
#8460
b101000 (
1#
1%
#8470
0#
0%
#8480
b101001 (
1#
1%
#8490
0#
0%
#8500
b101010 (
1#
1%
#8510
0#
0%
#8520
b101011 (
1#
1%
#8530
0#
0%
#8540
b101100 (
1#
1%
#8550
0#
0%
#8560
b101101 (
1#
1%
#8570
0#
0%
#8580
b101110 (
1#
1%
#8590
0#
0%
#8600
b101111 (
1#
1%
#8610
0#
0%
#8620
b110000 (
1#
1%
#8630
0#
0%
#8640
b110001 (
1#
1%
#8650
0#
0%
#8660
b110010 (
1#
1%
#8670
0#
0%
#8680
b110011 (
1#
1%
#8690
0#
0%
#8700
b110100 (
1#
1%
#8710
0#
0%
#8720
b110101 (
1#
1%
#8730
0#
0%
#8740
b110110 (
1#
1%
#8750
0#
0%
#8760
b110111 (
1#
1%
#8770
0#
0%
#8780
b111000 (
1#
1%
#8790
0#
0%
#8800
b111001 (
1#
1%
#8810
0#
0%
#8820
b111010 (
1#
1%
#8830
0#
0%
#8840
b111011 (
1#
1%
#8850
0#
0%
#8860
b111100 (
1#
1%
#8870
0#
0%
#8880
b111101 (
1#
1%
#8890
0#
0%
#8900
b111110 (
1#
1%
#8910
0#
0%
#8920
b111111 (
1#
1%
#8930
0#
0%
#8940
b1110 '
1!
b111 &
b0 (
1#
1%
#8950
0#
0%
#8960
b1 (
1#
1%
#8970
0#
0%
#8980
b10 (
1#
1%
#8990
0#
0%
#9000
b11 (
1#
1%
#9010
0#
0%
#9020
b100 (
1#
1%
#9030
0#
0%
#9040
b101 (
1#
1%
#9050
0#
0%
#9060
b110 (
1#
1%
#9070
0#
0%
#9080
b111 (
1#
1%
#9090
0#
0%
#9100
b1000 (
1#
1%
#9110
0#
0%
#9120
b1001 (
1#
1%
#9130
0#
0%
#9140
b1010 (
1#
1%
#9150
0#
0%
#9160
b1011 (
1#
1%
#9170
0#
0%
#9180
b1100 (
1#
1%
#9190
0#
0%
#9200
b1101 (
1#
1%
#9210
0#
0%
#9220
0!
b1110 (
1#
1%
#9230
0#
0%
#9240
b1111 (
1#
1%
#9250
0#
0%
#9260
b10000 (
1#
1%
#9270
0#
0%
#9280
b10001 (
1#
1%
#9290
0#
0%
#9300
b10010 (
1#
1%
#9310
0#
0%
#9320
b10011 (
1#
1%
#9330
0#
0%
#9340
b10100 (
1#
1%
#9350
0#
0%
#9360
b10101 (
1#
1%
#9370
0#
0%
#9380
b10110 (
1#
1%
#9390
0#
0%
#9400
b10111 (
1#
1%
#9410
0#
0%
#9420
b11000 (
1#
1%
#9430
0#
0%
#9440
b11001 (
1#
1%
#9450
0#
0%
#9460
b11010 (
1#
1%
#9470
0#
0%
#9480
b11011 (
1#
1%
#9490
0#
0%
#9500
b11100 (
1#
1%
#9510
0#
0%
#9520
b11101 (
1#
1%
#9530
0#
0%
#9540
b11110 (
1#
1%
#9550
0#
0%
#9560
b11111 (
1#
1%
#9570
0#
0%
#9580
b100000 (
1#
1%
#9590
0#
0%
#9600
b100001 (
1#
1%
#9610
0#
0%
#9620
b100010 (
1#
1%
#9630
0#
0%
#9640
b100011 (
1#
1%
#9650
0#
0%
#9660
b100100 (
1#
1%
#9670
0#
0%
#9680
b100101 (
1#
1%
#9690
0#
0%
#9700
b100110 (
1#
1%
#9710
0#
0%
#9720
b100111 (
1#
1%
#9730
0#
0%
#9740
b101000 (
1#
1%
#9750
0#
0%
#9760
b101001 (
1#
1%
#9770
0#
0%
#9780
b101010 (
1#
1%
#9790
0#
0%
#9800
b101011 (
1#
1%
#9810
0#
0%
#9820
b101100 (
1#
1%
#9830
0#
0%
#9840
b101101 (
1#
1%
#9850
0#
0%
#9860
b101110 (
1#
1%
#9870
0#
0%
#9880
b101111 (
1#
1%
#9890
0#
0%
#9900
b110000 (
1#
1%
#9910
0#
0%
#9920
b110001 (
1#
1%
#9930
0#
0%
#9940
b110010 (
1#
1%
#9950
0#
0%
#9960
b110011 (
1#
1%
#9970
0#
0%
#9980
b110100 (
1#
1%
#9990
0#
0%
#10000
b110101 (
1#
1%
#10010
0#
0%
#10020
b110110 (
1#
1%
#10030
0#
0%
#10040
b110111 (
1#
1%
#10050
0#
0%
#10060
b111000 (
1#
1%
#10070
0#
0%
#10080
b111001 (
1#
1%
#10090
0#
0%
#10100
b111010 (
1#
1%
#10110
0#
0%
#10120
b111011 (
1#
1%
#10130
0#
0%
#10140
b111100 (
1#
1%
#10150
0#
0%
#10160
b111101 (
1#
1%
#10170
0#
0%
#10180
b111110 (
1#
1%
#10190
0#
0%
#10200
b111111 (
1#
1%
#10210
0#
0%
#10220
b10000 '
1!
b1000 &
b0 (
1#
1%
#10230
0#
0%
#10240
b1 (
1#
1%
#10250
0#
0%
#10260
b10 (
1#
1%
#10270
0#
0%
#10280
b11 (
1#
1%
#10290
0#
0%
#10300
b100 (
1#
1%
#10310
0#
0%
#10320
b101 (
1#
1%
#10330
0#
0%
#10340
b110 (
1#
1%
#10350
0#
0%
#10360
b111 (
1#
1%
#10370
0#
0%
#10380
b1000 (
1#
1%
#10390
0#
0%
#10400
b1001 (
1#
1%
#10410
0#
0%
#10420
b1010 (
1#
1%
#10430
0#
0%
#10440
b1011 (
1#
1%
#10450
0#
0%
#10460
b1100 (
1#
1%
#10470
0#
0%
#10480
b1101 (
1#
1%
#10490
0#
0%
#10500
b1110 (
1#
1%
#10510
0#
0%
#10520
b1111 (
1#
1%
#10530
0#
0%
#10540
0!
b10000 (
1#
1%
#10550
0#
0%
#10560
b10001 (
1#
1%
#10570
0#
0%
#10580
b10010 (
1#
1%
#10590
0#
0%
#10600
b10011 (
1#
1%
#10610
0#
0%
#10620
b10100 (
1#
1%
#10630
0#
0%
#10640
b10101 (
1#
1%
#10650
0#
0%
#10660
b10110 (
1#
1%
#10670
0#
0%
#10680
b10111 (
1#
1%
#10690
0#
0%
#10700
b11000 (
1#
1%
#10710
0#
0%
#10720
b11001 (
1#
1%
#10730
0#
0%
